ekispert/__init__.py
ekispert/client.py
ekispert/utils.py
ekispert/__pycache__/__init__.cpython-311.pyc
ekispert/__pycache__/__init__.cpython-312.pyc
ekispert/__pycache__/__init__.cpython-313.pyc
ekispert/__pycache__/base.cpython-312.pyc
ekispert/__pycache__/base.cpython-313.pyc
ekispert/__pycache__/client.cpython-311.pyc
ekispert/__pycache__/client.cpython-312.pyc
ekispert/__pycache__/client.cpython-313.pyc
ekispert/__pycache__/model.cpython-312.pyc
ekispert/__pycache__/query.cpython-312.pyc
ekispert/__pycache__/utils.cpython-311.pyc
ekispert/models/base.py
ekispert/models/car.py
ekispert/models/change.py
ekispert/models/cost.py
ekispert/models/cource.py
ekispert/models/formation.py
ekispert/models/geo_point.py
ekispert/models/line.py
ekispert/models/operational_state.py
ekispert/models/pass_status.py
ekispert/models/point.py
ekispert/models/prefecture.py
ekispert/models/price.py
ekispert/models/relation.py
ekispert/models/repayment_list.py
ekispert/models/repayment_ticket.py
ekispert/models/route.py
ekispert/models/section_separator.py
ekispert/models/station.py
ekispert/models/stop.py
ekispert/models/teiki.py
ekispert/models/teiki_route.py
ekispert/models/teiki_route_section.py
ekispert/models/trip_option.py
ekispert/models/__pycache__/base.cpython-311.pyc
ekispert/models/__pycache__/car.cpython-311.pyc
ekispert/models/__pycache__/car.cpython-312.pyc
ekispert/models/__pycache__/car.cpython-313.pyc
ekispert/models/__pycache__/change.cpython-311.pyc
ekispert/models/__pycache__/change.cpython-312.pyc
ekispert/models/__pycache__/change.cpython-313.pyc
ekispert/models/__pycache__/cost.cpython-311.pyc
ekispert/models/__pycache__/cost.cpython-312.pyc
ekispert/models/__pycache__/cost.cpython-313.pyc
ekispert/models/__pycache__/cource.cpython-311.pyc
ekispert/models/__pycache__/cource.cpython-312.pyc
ekispert/models/__pycache__/cource.cpython-313.pyc
ekispert/models/__pycache__/ekispert_base.cpython-311.pyc
ekispert/models/__pycache__/formation.cpython-311.pyc
ekispert-0.5.0.dist-info/LICENSE
ekispert-0.5.0.dist-info/METADATA
ekispert-0.5.0.dist-info/WHEEL
ekispert-0.5.0.dist-info/entry_points.txt
ekispert-0.5.0.dist-info/top_level.txt
ekispert-0.5.0.dist-info/RECORD
