Metadata-Version: 2.2
Name: ekispert
Version: 0.5.0
Summary: SDK for Ekispert API
Home-page: https://github.com/EkispertMania/python_sdk
Author: Atsushi Nakatsugawa
Author-email: atsushi@moongift.co.jp
Classifier: Programming Language :: Python :: 3
Classifier: License :: OSI Approved :: MIT License
Classifier: Operating System :: OS Independent
Requires-Python: >=3.6
License-File: LICENSE
Requires-Dist: requests
Dynamic: author
Dynamic: author-email
Dynamic: classifier
Dynamic: description
Dynamic: description-content-type
Dynamic: home-page
Dynamic: requires-dist
Dynamic: requires-python
Dynamic: summary
